[ {
  "contractScope" : "ope523791",
  "energyCarrier" : "ELECTRICITY",
  "contractType" : "CONNECTION",
  "EnergyTransactionVolume_kWh" : 0.0,
  "FinancialTransactionVolume_eur" : 0.0,
  "contractHolder" : "con523794",
  "annualFee_eur" : 0.0,
  "connectionContractType" : "DEFAULT",
  "nfATOstart_h" : 0.0,
  "nfATOend_h" : 0.0,
  "nfATOpower_kW" : 0.0
}, {
  "contractScope" : "sup523793",
  "energyCarrier" : "ELECTRICITY",
  "contractType" : "DELIVERY",
  "EnergyTransactionVolume_kWh" : 0.0,
  "FinancialTransactionVolume_eur" : 0.0,
  "contractHolder" : "con523794",
  "annualFee_eur" : 0.0,
  "deliveryContractType" : "ELECTRICITY_VARIABLE",
  "deliveryPrice_eurpkWh" : 0.0,
  "feedinPrice_eurpkWh" : 0.0
}, {
  "contractScope" : "gov523795",
  "energyCarrier" : "ELECTRICITY",
  "contractType" : "TAX",
  "EnergyTransactionVolume_kWh" : 0.0,
  "FinancialTransactionVolume_eur" : 0.0,
  "contractHolder" : "con523794",
  "annualFee_eur" : 0.0,
  "deliveryTax_eurpkWh" : 0.15,
  "feedinTax_eurpkWh" : 0.15,
  "proportionalTax_pct" : 0.21
}, {
  "contractScope" : "ope523791",
  "energyCarrier" : "ELECTRICITY",
  "contractType" : "TRANSPORT",
  "EnergyTransactionVolume_kWh" : 0.0,
  "FinancialTransactionVolume_eur" : 0.0,
  "contractHolder" : "con523794",
  "annualFee_eur" : 0.0,
  "transportContractType" : "DEFAULT",
  "bandwidthTreshold_kW" : 0.0,
  "bandwidthTariff_eurpkWh" : 0.0
}, {
  "contractScope" : "sup523793",
  "energyCarrier" : "ELECTRICITY",
  "contractType" : "DELIVERY",
  "EnergyTransactionVolume_kWh" : 0.0,
  "FinancialTransactionVolume_eur" : 0.0,
  "contractHolder" : "con523796",
  "annualFee_eur" : 0.0,
  "deliveryContractType" : "ELECTRICITY_VARIABLE",
  "deliveryPrice_eurpkWh" : 0.0,
  "feedinPrice_eurpkWh" : 0.0
}, {
  "contractScope" : "ope523791",
  "energyCarrier" : "ELECTRICITY",
  "contractType" : "CONNECTION",
  "EnergyTransactionVolume_kWh" : 0.0,
  "FinancialTransactionVolume_eur" : 0.0,
  "contractHolder" : "con523796",
  "annualFee_eur" : 0.0,
  "connectionContractType" : "DEFAULT",
  "nfATOstart_h" : 20.0,
  "nfATOend_h" : 7.0,
  "nfATOpower_kW" : 2000.0
}, {
  "contractScope" : "gov523795",
  "energyCarrier" : "ELECTRICITY",
  "contractType" : "TAX",
  "EnergyTransactionVolume_kWh" : 0.0,
  "FinancialTransactionVolume_eur" : 0.0,
  "contractHolder" : "con523796",
  "annualFee_eur" : 0.0,
  "deliveryTax_eurpkWh" : 0.15,
  "feedinTax_eurpkWh" : 0.15,
  "proportionalTax_pct" : 0.21
}, {
  "contractScope" : "ope523791",
  "energyCarrier" : "ELECTRICITY",
  "contractType" : "TRANSPORT",
  "EnergyTransactionVolume_kWh" : 0.0,
  "FinancialTransactionVolume_eur" : 0.0,
  "contractHolder" : "con523796",
  "annualFee_eur" : 0.0,
  "transportContractType" : "DEFAULT",
  "bandwidthTreshold_kW" : 0.0,
  "bandwidthTariff_eurpkWh" : 0.0
}, {
  "contractScope" : "ope523791",
  "energyCarrier" : "ELECTRICITY",
  "contractType" : "CONNECTION",
  "EnergyTransactionVolume_kWh" : 0.0,
  "FinancialTransactionVolume_eur" : 0.0,
  "contractHolder" : "con523797",
  "annualFee_eur" : 0.0,
  "connectionContractType" : "DEFAULT",
  "nfATOstart_h" : 0.0,
  "nfATOend_h" : 0.0,
  "nfATOpower_kW" : 0.0
}, {
  "contractScope" : "sup523793",
  "energyCarrier" : "ELECTRICITY",
  "contractType" : "DELIVERY",
  "EnergyTransactionVolume_kWh" : 0.0,
  "FinancialTransactionVolume_eur" : 0.0,
  "contractHolder" : "con523797",
  "annualFee_eur" : 0.0,
  "deliveryContractType" : "ELECTRICITY_VARIABLE",
  "deliveryPrice_eurpkWh" : 0.0,
  "feedinPrice_eurpkWh" : 0.0
}, {
  "contractScope" : "gov523795",
  "energyCarrier" : "ELECTRICITY",
  "contractType" : "TAX",
  "EnergyTransactionVolume_kWh" : 0.0,
  "FinancialTransactionVolume_eur" : 0.0,
  "contractHolder" : "con523797",
  "annualFee_eur" : 0.0,
  "deliveryTax_eurpkWh" : 0.15,
  "feedinTax_eurpkWh" : 0.15,
  "proportionalTax_pct" : 0.21
}, {
  "contractScope" : "ope523791",
  "energyCarrier" : "ELECTRICITY",
  "contractType" : "TRANSPORT",
  "EnergyTransactionVolume_kWh" : 0.0,
  "FinancialTransactionVolume_eur" : 0.0,
  "contractHolder" : "con523797",
  "annualFee_eur" : 0.0,
  "transportContractType" : "DEFAULT",
  "bandwidthTreshold_kW" : 0.0,
  "bandwidthTariff_eurpkWh" : 0.0
}, {
  "contractScope" : "sup523793",
  "energyCarrier" : "ELECTRICITY",
  "contractType" : "DELIVERY",
  "EnergyTransactionVolume_kWh" : 0.0,
  "FinancialTransactionVolume_eur" : 0.0,
  "contractHolder" : "con523798",
  "annualFee_eur" : 0.0,
  "deliveryContractType" : "ELECTRICITY_VARIABLE",
  "deliveryPrice_eurpkWh" : 0.0,
  "feedinPrice_eurpkWh" : 0.0
}, {
  "contractScope" : "ope523791",
  "energyCarrier" : "ELECTRICITY",
  "contractType" : "CONNECTION",
  "EnergyTransactionVolume_kWh" : 0.0,
  "FinancialTransactionVolume_eur" : 0.0,
  "contractHolder" : "con523798",
  "annualFee_eur" : 0.0,
  "connectionContractType" : "DEFAULT",
  "nfATOstart_h" : 20.0,
  "nfATOend_h" : 7.0,
  "nfATOpower_kW" : 2000.0
}, {
  "contractScope" : "gov523795",
  "energyCarrier" : "ELECTRICITY",
  "contractType" : "TAX",
  "EnergyTransactionVolume_kWh" : 0.0,
  "FinancialTransactionVolume_eur" : 0.0,
  "contractHolder" : "con523798",
  "annualFee_eur" : 0.0,
  "deliveryTax_eurpkWh" : 0.15,
  "feedinTax_eurpkWh" : 0.15,
  "proportionalTax_pct" : 0.21
}, {
  "contractScope" : "ope523791",
  "energyCarrier" : "ELECTRICITY",
  "contractType" : "TRANSPORT",
  "EnergyTransactionVolume_kWh" : 0.0,
  "FinancialTransactionVolume_eur" : 0.0,
  "contractHolder" : "con523798",
  "annualFee_eur" : 0.0,
  "transportContractType" : "DEFAULT",
  "bandwidthTreshold_kW" : 0.0,
  "bandwidthTariff_eurpkWh" : 0.0
}, {
  "contractScope" : "sup523793",
  "energyCarrier" : "ELECTRICITY",
  "contractType" : "DELIVERY",
  "EnergyTransactionVolume_kWh" : 0.0,
  "FinancialTransactionVolume_eur" : -443781.0986178221,
  "contractHolder" : "con523799",
  "annualFee_eur" : 0.0,
  "deliveryContractType" : "ELECTRICITY_VARIABLE",
  "deliveryPrice_eurpkWh" : 0.0,
  "feedinPrice_eurpkWh" : 0.0
}, {
  "contractScope" : "ope523791",
  "energyCarrier" : "ELECTRICITY",
  "contractType" : "CONNECTION",
  "EnergyTransactionVolume_kWh" : 0.0,
  "FinancialTransactionVolume_eur" : 0.0,
  "contractHolder" : "con523799",
  "annualFee_eur" : 0.0,
  "connectionContractType" : "DEFAULT",
  "nfATOstart_h" : 0.0,
  "nfATOend_h" : 0.0,
  "nfATOpower_kW" : 0.0
}, {
  "contractScope" : "gov523795",
  "energyCarrier" : "ELECTRICITY",
  "contractType" : "TAX",
  "EnergyTransactionVolume_kWh" : 0.0,
  "FinancialTransactionVolume_eur" : -1817186.549433389,
  "contractHolder" : "con523799",
  "annualFee_eur" : 0.0,
  "deliveryTax_eurpkWh" : 0.15,
  "feedinTax_eurpkWh" : 0.15,
  "proportionalTax_pct" : 0.21
}, {
  "contractScope" : "ope523791",
  "energyCarrier" : "ELECTRICITY",
  "contractType" : "TRANSPORT",
  "EnergyTransactionVolume_kWh" : 0.0,
  "FinancialTransactionVolume_eur" : 0.0,
  "contractHolder" : "con523799",
  "annualFee_eur" : 0.0,
  "transportContractType" : "DEFAULT",
  "bandwidthTreshold_kW" : 0.0,
  "bandwidthTariff_eurpkWh" : 0.0
}, {
  "contractScope" : "sup523793",
  "energyCarrier" : "ELECTRICITY",
  "contractType" : "DELIVERY",
  "EnergyTransactionVolume_kWh" : 0.0,
  "FinancialTransactionVolume_eur" : 0.0,
  "contractHolder" : "hol523792",
  "annualFee_eur" : 0.0,
  "deliveryContractType" : "ELECTRICITY_VARIABLE",
  "deliveryPrice_eurpkWh" : 0.0,
  "feedinPrice_eurpkWh" : 0.0
}, {
  "contractScope" : "ope523791",
  "energyCarrier" : "ELECTRICITY",
  "contractType" : "TRANSPORT",
  "EnergyTransactionVolume_kWh" : 0.0,
  "FinancialTransactionVolume_eur" : 0.0,
  "contractHolder" : "hol523792",
  "annualFee_eur" : 0.0,
  "transportContractType" : "DEFAULT",
  "bandwidthTreshold_kW" : 0.0,
  "bandwidthTariff_eurpkWh" : 0.0
}, {
  "contractScope" : "gov523795",
  "energyCarrier" : "ELECTRICITY",
  "contractType" : "TAX",
  "EnergyTransactionVolume_kWh" : 0.0,
  "FinancialTransactionVolume_eur" : 0.0,
  "contractHolder" : "hol523792",
  "annualFee_eur" : 0.0,
  "deliveryTax_eurpkWh" : 0.15,
  "feedinTax_eurpkWh" : 0.15,
  "proportionalTax_pct" : 0.21
} ]