[ {
  "HSMSPeakLoadElectricity_kW" : 4936.79,
  "MSLSPeakLoadElectricity_kW" : 4936.79,
  "timesOfNodePeakLoads_h" : {
    "E1" : 2088.25,
    "E2" : 2088.25
  },
  "gridConnectionMaxLoad_fr" : {
    "b1" : 1.0,
    "b5" : 1.0,
    "b2" : 0.8661908868961566,
    "b3" : 0.8847556255197815,
    "b4" : 0.5719018701108075
  },
  "MSLSnodePeakPositiveLoadElectricity_kW" : 4936.791254406839,
  "MSLSnodePeakNegativeLoadElectricity_kW" : 4578.7590871335515,
  "totalElectricityImport_MWh" : 16271.96,
  "totalElectricityExport_MWh" : 6107.37,
  "totalMethaneImport_MWh" : 631.6,
  "totalMethaneExport_MWh" : 0.0,
  "totalHydrogenImport_MWh" : 0.0,
  "totalHydrogenExport_MWh" : 0.0,
  "totalDieselImport_MWh" : 0.0,
  "totalBatteryUnitsInstalled" : {
    "EHGV" : 20.0,
    "Grid_battery" : 1.0
  },
  "totalBatteryChargeAmount_MWh" : {
    "EHGV" : 21588.49,
    "Grid_battery" : 2823.1882490516928
  },
  "totalBatteryDischargeAmount_MWh" : {
    "EHGV" : 0.0,
    "Grid_battery" : 2803.9574289808625
  },
  "totalBatteryInstalledCapacity_MWh" : {
    "EHGV" : 100.0,
    "Grid_battery" : 35.0
  },
  "totalSelfConsumption_fr" : 0.7151632376619426,
  "totalSelfSufficiency_fr" : 0.47538017225956763,
  "TotalEnergyUsed_MWh" : 32256.940000000002,
  "TotalEnergyProduced_MWh" : 21441.66
} ]